{
  "robotId": "simforge-warehouse-manipulator-v1",
  "environmentId": "simforge-warehouse-demo-v1",
  "counts": {
    "links": 12,
    "joints": 11,
    "sensors": 3,
    "environmentObjects": 15
  },
  "defect": {
    "ruleId": "ROB-LINK-POSE-001",
    "sceneRevision": 2
  },
  "correctedSceneRevision": 3,
  "review": {
    "before": "02201b917b56933186cbe14ea72420e32d88350e5834526b161267f3db1cf6e4",
    "after": "f5f632bc1861af3e1e7411fdaec59b5f5c8f99a99066e339e2217797e8bf4d40",
    "overview": "b587d5cb250094b00cf0dfca0f15a46de128ca7e388072328ddfb311f1926bd5"
  },
  "export": {
    "exportId": "cd98d7bd-5cb7-4099-baa8-6cbe62235229",
    "checks": [
      {
        "evidence": {
          "missing": [],
          "required": [
            "scene.usda",
            "robot/robot.usda",
            "robot/geometry/robot_geometry.usdc",
            "robot/materials/robot_materials.usda",
            "robot/physics/robot_physics.usda",
            "robot/sensors/robot_sensors.usda",
            "environment/environment.usda",
            "environment/environment_geometry.usdc"
          ]
        },
        "id": "USD-LAYERS-001",
        "status": "PASS"
      },
      {
        "evidence": {
          "entryPoint": "scene.usda"
        },
        "id": "USD-STAGE-001",
        "status": "PASS"
      },
      {
        "evidence": {
          "defaultPrim": "/World",
          "metersPerUnit": 1,
          "upAxis": "Z"
        },
        "id": "USD-CONVENTION-001",
        "status": "PASS"
      },
      {
        "evidence": {
          "invalid": [],
          "references": [
            {
              "asset": "./environment/environment.usda",
              "layer": "scene.usda"
            },
            {
              "asset": "./robot/robot.usda",
              "layer": "scene.usda"
            },
            {
              "asset": "./materials/robot_materials.usda",
              "layer": "robot/robot.usda"
            },
            {
              "asset": "./physics/robot_physics.usda",
              "layer": "robot/robot.usda"
            },
            {
              "asset": "./sensors/robot_sensors.usda",
              "layer": "robot/robot.usda"
            },
            {
              "asset": "./geometry/robot_geometry.usdc",
              "layer": "robot/robot.usda"
            },
            {
              "asset": "./materials/robot_materials.usda",
              "layer": "robot/robot.usda"
            },
            {
              "asset": "./physics/robot_physics.usda",
              "layer": "robot/robot.usda"
            },
            {
              "asset": "./sensors/robot_sensors.usda",
              "layer": "robot/robot.usda"
            },
            {
              "asset": "./environment_geometry.usdc",
              "layer": "environment/environment.usda"
            }
          ]
        },
        "id": "USD-REFERENCES-001",
        "status": "PASS"
      },
      {
        "evidence": {
          "articulationRoot": true,
          "joints": 11,
          "links": 12,
          "visualAndPhysicsLinkPrims": 24
        },
        "id": "USD-ROBOT-001",
        "status": "PASS"
      },
      {
        "evidence": {
          "collisions": 12,
          "massSchemas": 12
        },
        "id": "USD-PHYSICS-001",
        "status": "PASS"
      },
      {
        "evidence": {
          "materials": 5
        },
        "id": "USD-MATERIAL-001",
        "status": "PASS"
      },
      {
        "evidence": {
          "sensors": 3
        },
        "id": "USD-SENSOR-001",
        "status": "PASS"
      },
      {
        "evidence": {
          "environmentId": "simforge-warehouse-demo-v1",
          "expectedObjects": 15,
          "objects": 15,
          "placeholder": false
        },
        "id": "USD-ENVIRONMENT-001",
        "status": "PASS"
      },
      {
        "evidence": {
          "failures": [],
          "fileCount": 23
        },
        "id": "USD-HASH-001",
        "status": "PASS"
      },
      {
        "evidence": {
          "articulationRoot": true,
          "collisions": 12,
          "joints": 11,
          "links": 12,
          "materials": 5,
          "metersPerUnit": 1,
          "sensors": 3,
          "traversedPrims": 173,
          "upAxis": "Z",
          "usedLayers": 9
        },
        "id": "USD-DEEP-REOPEN-001",
        "status": "PASS"
      },
      {
        "evidence": {
          "entryPoint": "scene.usda",
          "failures": [],
          "reopenedAtCurrentLocation": true
        },
        "id": "USD-PORTABILITY-001",
        "status": "PASS"
      }
    ],
    "movedReopen": true
  },
  "isaacFeedback": {
    "beforeExperimentId": "8758c392-beb2-49b9-84b1-9550cbc2f8e6",
    "beforeStatus": "FAILED",
    "analysisStatus": "CORRECTION_PROPOSED",
    "correction": {
      "rootLinkId": "arm_column_link",
      "deltaXM": -0.12477,
      "checkpointId": "ec28026a-ac3d-4ba2-9a79-d97bee6e29bb",
      "sceneRevision": 4
    },
    "correctedExportId": "8db798ee-86ab-4bf0-91d8-f05c038b6bff",
    "afterExperimentId": "a23c4f3c-cbd5-424d-9fc0-e1309111b4b9",
    "afterStatus": "PASSED",
    "parentExperimentId": "8758c392-beb2-49b9-84b1-9550cbc2f8e6"
  }
}
